setup.cfg
setup.py
repoze/__init__.py
repoze.who.plugins.recaptcha.egg-info/PKG-INFO
repoze.who.plugins.recaptcha.egg-info/SOURCES.txt
repoze.who.plugins.recaptcha.egg-info/dependency_links.txt
repoze.who.plugins.recaptcha.egg-info/entry_points.txt
repoze.who.plugins.recaptcha.egg-info/namespace_packages.txt
repoze.who.plugins.recaptcha.egg-info/not-zip-safe
repoze.who.plugins.recaptcha.egg-info/requires.txt
repoze.who.plugins.recaptcha.egg-info/top_level.txt
repoze/who/__init__.py
repoze/who/plugins/__init__.py
repoze/who/plugins/captcha.py
repoze/who/plugins/test_captcha.py