Metadata-Version: 1.0
Name: repoze.who.plugins.recaptcha
Version: 0.2
Summary: recaptcha repoze.who plugin implementation
Home-page: UNKNOWN
Author: Domen "iElectric" Kozar
Author-email: domen@dev.si
License: BSD-derived (http://www.repoze.org/LICENSE.txt)
Keywords: repoze.who captcha
Platform: UNKNOWN
Classifier: Programming Language :: Python
Classifier: Topic :: Software Development :: Libraries :: Python Modules
Classifier: Development Status :: 3 - Alpha
